<annotation>
	<folder></folder>
	<filename>11137_jpg.rf.e430cc727831428296ea87ebad7c8985.jpg</filename>
	<path>11137_jpg.rf.e430cc727831428296ea87ebad7c8985.jpg</path>
	<source>
		<database>roboflow.com</database>
	</source>
	<size>
		<width>640</width>
		<height>640</height>
		<depth>3</depth>
	</size>
	<segmented>0</segmented>
	<object>
		<name>human</name>
		<pose>Unspecified</pose>
		<truncated>0</truncated>
		<difficult>0</difficult>
		<occluded>0</occluded>
		<bndbox>
			<xmin>424</xmin>
			<xmax>496</xmax>
			<ymin>67</ymin>
			<ymax>174</ymax>
		</bndbox>
	</object>
	<object>
		<name>human</name>
		<pose>Unspecified</pose>
		<truncated>0</truncated>
		<difficult>0</difficult>
		<occluded>0</occluded>
		<bndbox>
			<xmin>572</xmin>
			<xmax>636</xmax>
			<ymin>270</ymin>
			<ymax>388</ymax>
		</bndbox>
	</object>
	<object>
		<name>human</name>
		<pose>Unspecified</pose>
		<truncated>0</truncated>
		<difficult>0</difficult>
		<occluded>0</occluded>
		<bndbox>
			<xmin>361</xmin>
			<xmax>432</xmax>
			<ymin>440</ymin>
			<ymax>534</ymax>
		</bndbox>
	</object>
</annotation>
