<annotation>
	<folder></folder>
	<filename>fishing-0033_bmp_jpg.rf.38f90f482a75921c9ca334210e35b7c8.jpg</filename>
	<path>fishing-0033_bmp_jpg.rf.38f90f482a75921c9ca334210e35b7c8.jpg</path>
	<source>
		<database>roboflow.com</database>
	</source>
	<size>
		<width>640</width>
		<height>640</height>
		<depth>3</depth>
	</size>
	<segmented>0</segmented>
	<object>
		<name>fishing ship</name>
		<pose>Unspecified</pose>
		<truncated>0</truncated>
		<difficult>0</difficult>
		<occluded>0</occluded>
		<bndbox>
			<xmin>261</xmin>
			<xmax>400</xmax>
			<ymin>226</ymin>
			<ymax>324</ymax>
		</bndbox>
	</object>
</annotation>
