<annotation>
	<folder></folder>
	<filename>google_0372_jpg.rf.0142111bb67ea25f7f5876ebc1d1eadb.jpg</filename>
	<path>google_0372_jpg.rf.0142111bb67ea25f7f5876ebc1d1eadb.jpg</path>
	<source>
		<database>roboflow.com</database>
	</source>
	<size>
		<width>640</width>
		<height>640</height>
		<depth>3</depth>
	</size>
	<segmented>0</segmented>
	<object>
		<name>buoy</name>
		<pose>Unspecified</pose>
		<truncated>0</truncated>
		<difficult>0</difficult>
		<occluded>0</occluded>
		<bndbox>
			<xmin>273</xmin>
			<xmax>358</xmax>
			<ymin>325</ymin>
			<ymax>452</ymax>
		</bndbox>
	</object>
</annotation>
