<annotation>
	<folder></folder>
	<filename>corrosion-780x300_jpg.rf.e9394496bc3e85d089cab74681cc6a7b.jpg</filename>
	<path>corrosion-780x300_jpg.rf.e9394496bc3e85d089cab74681cc6a7b.jpg</path>
	<source>
		<database>roboflow.ai</database>
	</source>
	<size>
		<width>640</width>
		<height>640</height>
		<depth>3</depth>
	</size>
	<segmented>0</segmented>
	<object>
		<name>hole</name>
		<pose>Unspecified</pose>
		<truncated>0</truncated>
		<difficult>0</difficult>
		<occluded>0</occluded>
		<bndbox>
			<xmin>373</xmin>
			<xmax>406</xmax>
			<ymin>381</ymin>
			<ymax>402</ymax>
		</bndbox>
	</object>
	<object>
		<name>hole</name>
		<pose>Unspecified</pose>
		<truncated>0</truncated>
		<difficult>0</difficult>
		<occluded>0</occluded>
		<bndbox>
			<xmin>218</xmin>
			<xmax>308</xmax>
			<ymin>354</ymin>
			<ymax>413</ymax>
		</bndbox>
	</object>
	<object>
		<name>hole</name>
		<pose>Unspecified</pose>
		<truncated>0</truncated>
		<difficult>0</difficult>
		<occluded>0</occluded>
		<bndbox>
			<xmin>192</xmin>
			<xmax>268</xmax>
			<ymin>267</ymin>
			<ymax>311</ymax>
		</bndbox>
	</object>
	<object>
		<name>hole</name>
		<pose>Unspecified</pose>
		<truncated>0</truncated>
		<difficult>0</difficult>
		<occluded>0</occluded>
		<bndbox>
			<xmin>132</xmin>
			<xmax>182</xmax>
			<ymin>262</ymin>
			<ymax>294</ymax>
		</bndbox>
	</object>
	<object>
		<name>hole</name>
		<pose>Unspecified</pose>
		<truncated>0</truncated>
		<difficult>0</difficult>
		<occluded>0</occluded>
		<bndbox>
			<xmin>513</xmin>
			<xmax>559</xmax>
			<ymin>351</ymin>
			<ymax>375</ymax>
		</bndbox>
	</object>
</annotation>
