<annotation>
	<folder></folder>
	<filename>images-4-_jpg.rf.73f16541ca23457e9b14c0ca6e1528c1.jpg</filename>
	<path>images-4-_jpg.rf.73f16541ca23457e9b14c0ca6e1528c1.jpg</path>
	<source>
		<database>roboflow.ai</database>
	</source>
	<size>
		<width>640</width>
		<height>640</height>
		<depth>3</depth>
	</size>
	<segmented>0</segmented>
	<object>
		<name>hole</name>
		<pose>Unspecified</pose>
		<truncated>0</truncated>
		<difficult>0</difficult>
		<occluded>0</occluded>
		<bndbox>
			<xmin>455</xmin>
			<xmax>495</xmax>
			<ymin>117</ymin>
			<ymax>175</ymax>
		</bndbox>
	</object>
	<object>
		<name>hole</name>
		<pose>Unspecified</pose>
		<truncated>0</truncated>
		<difficult>0</difficult>
		<occluded>0</occluded>
		<bndbox>
			<xmin>440</xmin>
			<xmax>641</xmax>
			<ymin>102</ymin>
			<ymax>339</ymax>
		</bndbox>
	</object>
	<object>
		<name>rupture</name>
		<pose>Unspecified</pose>
		<truncated>0</truncated>
		<difficult>0</difficult>
		<occluded>0</occluded>
		<bndbox>
			<xmin>519</xmin>
			<xmax>641</xmax>
			<ymin>376</ymin>
			<ymax>498</ymax>
		</bndbox>
	</object>
	<object>
		<name>hole</name>
		<pose>Unspecified</pose>
		<truncated>0</truncated>
		<difficult>0</difficult>
		<occluded>0</occluded>
		<bndbox>
			<xmin>82</xmin>
			<xmax>119</xmax>
			<ymin>115</ymin>
			<ymax>132</ymax>
		</bndbox>
	</object>
	<object>
		<name>hole</name>
		<pose>Unspecified</pose>
		<truncated>0</truncated>
		<difficult>0</difficult>
		<occluded>0</occluded>
		<bndbox>
			<xmin>137</xmin>
			<xmax>230</xmax>
			<ymin>106</ymin>
			<ymax>151</ymax>
		</bndbox>
	</object>
	<object>
		<name>hole</name>
		<pose>Unspecified</pose>
		<truncated>0</truncated>
		<difficult>0</difficult>
		<occluded>0</occluded>
		<bndbox>
			<xmin>190</xmin>
			<xmax>264</xmax>
			<ymin>161</ymin>
			<ymax>195</ymax>
		</bndbox>
	</object>
	<object>
		<name>hole</name>
		<pose>Unspecified</pose>
		<truncated>0</truncated>
		<difficult>0</difficult>
		<occluded>0</occluded>
		<bndbox>
			<xmin>250</xmin>
			<xmax>303</xmax>
			<ymin>172</ymin>
			<ymax>198</ymax>
		</bndbox>
	</object>
	<object>
		<name>hole</name>
		<pose>Unspecified</pose>
		<truncated>0</truncated>
		<difficult>0</difficult>
		<occluded>0</occluded>
		<bndbox>
			<xmin>24</xmin>
			<xmax>35</xmax>
			<ymin>133</ymin>
			<ymax>146</ymax>
		</bndbox>
	</object>
	<object>
		<name>rupture</name>
		<pose>Unspecified</pose>
		<truncated>0</truncated>
		<difficult>0</difficult>
		<occluded>0</occluded>
		<bndbox>
			<xmin>143</xmin>
			<xmax>197</xmax>
			<ymin>439</ymin>
			<ymax>492</ymax>
		</bndbox>
		<polygon>
			<x1>142.557319</x1>
			<y1>446.43756</y1>
			<x2>142.302096</x2>
			<y2>456.353254</y2>
			<x3>151.315941</x3>
			<y3>466.560944</y3>
			<x4>160.123742</x4>
			<y4>475.332109</y4>
			<x5>181.708972</x5>
			<y5>491.309375</y5>
			<x6>195.615094</x6>
			<y6>482.993749</y6>
			<x7>167.999393</x7>
			<y7>454.216004</y7>
			<x8>148.067137</x8>
			<y8>438.121097</y8>
			<x9>142.557319</x9>
			<y9>446.43756</y9>
		</polygon>
	</object>
</annotation>
