<annotation>
	<folder></folder>
	<filename>e53964d7afa9453badb18747b66c93f8_jpg.rf.2397e9891ed3b5e40419e2d044355e91.jpg</filename>
	<path>e53964d7afa9453badb18747b66c93f8_jpg.rf.2397e9891ed3b5e40419e2d044355e91.jpg</path>
	<source>
		<database>roboflow.ai</database>
	</source>
	<size>
		<width>640</width>
		<height>640</height>
		<depth>3</depth>
	</size>
	<segmented>0</segmented>
	<object>
		<name>hole</name>
		<pose>Unspecified</pose>
		<truncated>0</truncated>
		<difficult>0</difficult>
		<occluded>0</occluded>
		<bndbox>
			<xmin>318</xmin>
			<xmax>344</xmax>
			<ymin>1</ymin>
			<ymax>40</ymax>
		</bndbox>
	</object>
	<object>
		<name>hole</name>
		<pose>Unspecified</pose>
		<truncated>0</truncated>
		<difficult>0</difficult>
		<occluded>0</occluded>
		<bndbox>
			<xmin>408</xmin>
			<xmax>446</xmax>
			<ymin>40</ymin>
			<ymax>84</ymax>
		</bndbox>
	</object>
	<object>
		<name>hole</name>
		<pose>Unspecified</pose>
		<truncated>0</truncated>
		<difficult>0</difficult>
		<occluded>0</occluded>
		<bndbox>
			<xmin>390</xmin>
			<xmax>431</xmax>
			<ymin>3</ymin>
			<ymax>56</ymax>
		</bndbox>
	</object>
	<object>
		<name>hole</name>
		<pose>Unspecified</pose>
		<truncated>0</truncated>
		<difficult>0</difficult>
		<occluded>0</occluded>
		<bndbox>
			<xmin>445</xmin>
			<xmax>486</xmax>
			<ymin>27</ymin>
			<ymax>78</ymax>
		</bndbox>
	</object>
	<object>
		<name>hole</name>
		<pose>Unspecified</pose>
		<truncated>0</truncated>
		<difficult>0</difficult>
		<occluded>0</occluded>
		<bndbox>
			<xmin>576</xmin>
			<xmax>626</xmax>
			<ymin>78</ymin>
			<ymax>163</ymax>
		</bndbox>
	</object>
	<object>
		<name>hole</name>
		<pose>Unspecified</pose>
		<truncated>0</truncated>
		<difficult>0</difficult>
		<occluded>0</occluded>
		<bndbox>
			<xmin>468</xmin>
			<xmax>630</xmax>
			<ymin>1</ymin>
			<ymax>151</ymax>
		</bndbox>
	</object>
	<object>
		<name>hole</name>
		<pose>Unspecified</pose>
		<truncated>0</truncated>
		<difficult>0</difficult>
		<occluded>0</occluded>
		<bndbox>
			<xmin>146</xmin>
			<xmax>181</xmax>
			<ymin>27</ymin>
			<ymax>69</ymax>
		</bndbox>
	</object>
	<object>
		<name>hole</name>
		<pose>Unspecified</pose>
		<truncated>0</truncated>
		<difficult>0</difficult>
		<occluded>0</occluded>
		<bndbox>
			<xmin>216</xmin>
			<xmax>249</xmax>
			<ymin>339</ymin>
			<ymax>400</ymax>
		</bndbox>
	</object>
	<object>
		<name>hole</name>
		<pose>Unspecified</pose>
		<truncated>0</truncated>
		<difficult>0</difficult>
		<occluded>0</occluded>
		<bndbox>
			<xmin>301</xmin>
			<xmax>375</xmax>
			<ymin>267</ymin>
			<ymax>350</ymax>
		</bndbox>
	</object>
	<object>
		<name>crack</name>
		<pose>Unspecified</pose>
		<truncated>0</truncated>
		<difficult>0</difficult>
		<occluded>0</occluded>
		<bndbox>
			<xmin>349</xmin>
			<xmax>516</xmax>
			<ymin>293</ymin>
			<ymax>417</ymax>
		</bndbox>
	</object>
	<object>
		<name>crack</name>
		<pose>Unspecified</pose>
		<truncated>0</truncated>
		<difficult>0</difficult>
		<occluded>0</occluded>
		<bndbox>
			<xmin>1</xmin>
			<xmax>187</xmax>
			<ymin>376</ymin>
			<ymax>536</ymax>
		</bndbox>
		<polygon>
			<x1>0</x1>
			<y1>409.566733</y1>
			<x2>35.307548</x2>
			<y2>419.971323</y2>
			<x3>67.659203</x3>
			<y3>448.693717</y3>
			<x4>100.12289</x4>
			<y4>461.125344</y4>
			<x5>133.527473</x5>
			<y5>486.061101</y5>
			<x6>151.928615</x6>
			<y6>507.962528</y6>
			<x7>178.901682</x7>
			<y7>535.178662</y7>
			<x8>185.940231</x8>
			<y8>509.845063</y8>
			<x9>167.12397</x9>
			<y9>489.583416</y9>
			<x10>84.625405</x10>
			<y10>426.018675</y10>
			<x11>27.626959</x11>
			<y11>384.385196</y11>
			<x12>0</x12>
			<y12>375.304773</y12>
			<x13>0</x13>
			<y13>409.566733</y13>
		</polygon>
	</object>
</annotation>
